{
    "Adventure HQ": {
        "img_list": [
            "https://cdn2.apstatic.com/photos/climb/118097136_smallMed_1574809380.jpg",
            "https://cdn2.apstatic.com/photos/climb/118097147_smallMed_1574809571.jpg",
            "https://cdn2.apstatic.com/photos/climb/118097155_smallMed_1574809716.jpg"
        ],
        "gym_info": [
            "",
            " 5270 N US HWY 1, Palm Shores, FL 32940 "
        ]
    },
    "Aiguille Rock Climbing Center": {
        "img_list": [
            "https://cdn2.apstatic.com/photos/climb/117068333_smallMed_1559598317.jpg",
            "https://cdn2.apstatic.com/photos/climb/117559037_smallMed_1565152196.jpg"
        ],
        "gym_info": [
            "www.aiguille.com",
            " 999 Charles St, Longwood, Florida 32750 "
        ]
    },
    "Beaches Rock Gym": {
        "img_list": [],
        "gym_info": [
            " 14 W 3rd St Atlantic Beach, FL 32233 "
        ]
    },
    "Blue Swan Boulders": {
        "img_list": [],
        "gym_info": [
            "blueswanboulders.com",
            " 400 Pittman St Suite 103, Orlando, FL 32801 "
        ]
    },
    "Boca Prep International School": {
        "img_list": [],
        "gym_info": [
            "www.bocaprep.net",
            " 10333 Diego Dr., Boca Raton, Florida "
        ]
    },
    "Boys and Girls Club": {
        "img_list": [],
        "gym_info": [
            "www.boysandgirlsclubs.com",
            " 1300 Fruitville Road, Sarasota, Florida 34219, (941) 366 7940 "
        ]
    },
    "Broward College South Campus": {
        "img_list": [],
        "gym_info": [
            "www.broward.edu",
            " 7200 Pines Boulevard, Building 65, Room 154 (Gymnasium), Pembroke Pines, Florida 33024 "
        ]
    },
    "Coral Cliffs indoor rock climbing wall": {
        "img_list": [],
        "gym_info": [
            "www.coralcliffs.com",
            " 3400 Southwest 26th Terrace #A4, Fort Lauderdale, Florida 33312 "
        ]
    },
    "Coral Square Mall": {
        "img_list": [],
        "gym_info": [
            " 9469 West Atlantic Boulevard, Coral Springs, Florida 33071 "
        ]
    },
    "Cornerstone Rock Gym": {
        "img_list": [],
        "gym_info": [
            "cornerstonerockgym.com",
            " 6746 Mt Vernon St, Glen St Mary, FL 32040 "
        ]
    },
    "Daytona Lagoon": {
        "img_list": [],
        "gym_info": [
            "www.daytonalagoon.com",
            " 601 Earl St., Daytona Beach Florida 32118 "
        ]
    },
    "DynoClimb": {
        "img_list": [
            "https://cdn2.apstatic.com/photos/climb/117968132_smallMed_1572447049.jpg"
        ],
        "gym_info": [
            "www.dynoclimb.com",
            " 528 S Woodland Blvd, DeLand, FL 32720 "
        ]
    },
    "Livingston's Amusement Center": {
        "img_list": [],
        "gym_info": [
            "www.LivingstonsAmusements.com",
            " 5947 Clark Center Ave, Sarasota, Florida 34238 "
        ]
    },
    "On The Edge Rock Climbing Gym": {
        "img_list": [
            "https://cdn2.apstatic.com/photos/climb/117068345_smallMed_1559598422.jpg"
        ],
        "gym_info": [
            "www.ontheedgerockclimbing.com",
            " 200 West Drive - Melbourne, Florida 32904 "
        ]
    },
    "Project Rock": {
        "img_list": [
            "https://cdn2.apstatic.com/photos/climb/117818551_smallMed_1569936700.jpg",
            "https://cdn2.apstatic.com/photos/climb/117845069_smallMed_1570418620.jpg",
            "https://cdn2.apstatic.com/photos/climb/117845088_smallMed_1570418765.jpg",
            "https://cdn2.apstatic.com/photos/climb/120265332_smallMed_1612575420.jpg",
            "https://cdn2.apstatic.com/photos/climb/120265335_smallMed_1612575502.jpg",
            "https://cdn2.apstatic.com/photos/climb/120265341_smallMed_1612575580.jpg"
        ],
        "gym_info": [
            "projectrock.com",
            " 3580 N Andrews Ave, Oakland Park FL 33309 "
        ]
    },
    "Rec Rock": {
        "img_list": [],
        "gym_info": [
            "www.cityofoviedo.net",
            " 148 Oviedo Blvd. Oviedo, FL 32765 "
        ]
    },
    "Red Dragon Kenpo Karate": {
        "img_list": [],
        "gym_info": [
            "www.reddragonkenpokarate.com",
            " 18070 S. Tamiami Trail, Fort Myers, Florida 33908 "
        ]
    },
    "Rock Out Climbing Gym": {
        "img_list": [],
        "gym_info": [
            "www.rockoutclimbing.com",
            " 2001 98 Palms Blvd Ste 5, Destin, Florida 32541 "
        ]
    },
    "Sarasota Family YMCA": {
        "img_list": [],
        "gym_info": [
            "www.sarasota-ymca.org",
            " 8301 Potter Park Dr, Sarasota, Florida 34238 "
        ]
    },
    "Sheinberg Family YMCA of Weston": {
        "img_list": [],
        "gym_info": [
            "www.ymcabroward.org",
            " 20201 Saddle Club Road, Weston, Florida 33327 "
        ]
    },
    "Sun Country Rocks": {
        "img_list": [],
        "gym_info": [
            "suncountryrocks.com",
            " 333 SW 140th Terrace, Gainesville, Florida 32669 "
        ]
    },
    "Tallahassee Rock Gym": {
        "img_list": [],
        "gym_info": [
            "www.tallyrockgym.com",
            " 629 F Industrial Dr, Tallahassee, Florida 32310 "
        ]
    },
    "The Edge Rock Gym": {
        "img_list": [],
        "gym_info": [
            "www.theedgerockgym.com",
            " 3563 Phillips Hwy., Suite 702, Jacksonville, Florida 32207 "
        ]
    },
    "UCF Recreational Center Rock Tower": {
        "img_list": [],
        "gym_info": [
            "www.rec.ucf.edu",
            " 4000 Central Florida Blvd, Orlando, Florida 32816 "
        ]
    },
    "University Climbing Wall": {
        "img_list": [],
        "gym_info": [
            " Florida Atlantic University AV Building - near library, 777 Glades Road "
        ]
    },
    "UWF Climbing Center": {
        "img_list": [],
        "gym_info": [
            "uwf.edu",
            " 11000 University Pkwy., Pensacola, FL 32514 "
        ]
    },
    "Vertical Ventures": {
        "img_list": [],
        "gym_info": [
            "www.verticalventures.com",
            " 5402 Suite-E Pioneer Park Blvd, Tampa, Florida 33634 "
        ]
    },
    "Vertical Ventures: St. Pete": {
        "img_list": [],
        "gym_info": [
            "stpete.verticalventures.com",
            " 116 18th St S, St. Petersburg, FL 33712 "
        ]
    },
    "Weatherford's Climbing Wall": {
        "img_list": [
            "https://cdn2.apstatic.com/photos/climb/118644387_smallMed_1584044710.jpg"
        ],
        "gym_info": [
            "www.weatherfordsoutback.com",
            " 3009 E. Cervantes St, Pensacola, Florida 32503 "
        ]
    },
    "X-treme: The Rock Climbing Center": {
        "img_list": [],
        "gym_info": [
            "www.x-tremerock.com",
            " 13972 SW 139th Ct, Miami, Florida 33186 "
        ]
    },
    "YMCA of Greater St. Petersburg": {
        "img_list": [],
        "gym_info": [
            "www.stpeteymca.org",
            " 3200 First Ave. South, St. Petersburg, FL "
        ]
    }
}